hasard/README.md
hasard/__init__.py
hasard/envs/armament_burden/conf.cfg
hasard/envs/armament_burden/level_1.wad
hasard/envs/armament_burden/level_1_hard.wad
hasard/envs/armament_burden/level_2.wad
hasard/envs/armament_burden/level_3.wad
hasard/envs/collateral_damage/conf.cfg
hasard/envs/collateral_damage/level_1.wad
hasard/envs/collateral_damage/level_1_hard.wad
hasard/envs/collateral_damage/level_2.wad
hasard/envs/collateral_damage/level_3.wad
hasard/envs/detonators_dilemma/conf.cfg
hasard/envs/detonators_dilemma/level_1.wad
hasard/envs/detonators_dilemma/level_1_hard.wad
hasard/envs/detonators_dilemma/level_2.wad
hasard/envs/detonators_dilemma/level_3.wad
hasard/envs/precipice_plunge/conf.cfg
hasard/envs/precipice_plunge/level_1.wad
hasard/envs/precipice_plunge/level_1_hard.wad
hasard/envs/precipice_plunge/level_2.wad
hasard/envs/precipice_plunge/level_3.wad
hasard/envs/remedy_rush/conf.cfg
hasard/envs/remedy_rush/level_1.wad
hasard/envs/remedy_rush/level_1_hard.wad
hasard/envs/remedy_rush/level_2.wad
hasard/envs/remedy_rush/level_3.wad
hasard/envs/volcanic_venture/conf.cfg
hasard/envs/volcanic_venture/level_1.wad
hasard/envs/volcanic_venture/level_1_hard.wad
hasard/envs/volcanic_venture/level_2.wad
hasard/envs/volcanic_venture/level_3.wad
sample_factory/README.md
sample_factory/__init__.py
sample_factory/enjoy.py
sample_factory/eval.py
sample_factory/record_gameplay.py
sample_factory/train.py
sample_factory/algo/__init__.py
sample_factory/algo/evaluators/__init__.py
sample_factory/algo/evaluators/default_evaluator.py
sample_factory/algo/learning/__init__.py
sample_factory/algo/learning/batcher.py
sample_factory/algo/learning/cpo_learner.py
sample_factory/algo/learning/cpo_learner_new.py
sample_factory/algo/learning/learner_worker.py
sample_factory/algo/learning/p3o_learner.py
sample_factory/algo/learning/pid_lagrangian.py
sample_factory/algo/learning/ppo_detached_learner.py
sample_factory/algo/learning/ppo_lag_learner.py
HASARD-0.2.0.dist-info/LICENSE
HASARD-0.2.0.dist-info/METADATA
HASARD-0.2.0.dist-info/WHEEL
HASARD-0.2.0.dist-info/top_level.txt
HASARD-0.2.0.dist-info/RECORD
