Metadata-Version: 2.1
Name: HASARD
Version: 0.2.0
Summary: Egocentric 3D Safe Reinforcement Learning Benchmark
Home-page: https://github.com/TTomilin/HASARD
Author: Tristan Tomilin
Author-email: tristan.tomilin@hotmail.com
License: MIT
Keywords: safe rl,reinforcement learning,vizdoom,benchmark,safety
Requires-Python: >=3.8
License-File: LICENSE
Requires-Dist: numpy <2.0,>=1.18.1
Requires-Dist: gymnasium <1.0,>=0.27
Requires-Dist: pyglet
Requires-Dist: opencv-python
Requires-Dist: vizdoom
Requires-Dist: pillow
Provides-Extra: results
Requires-Dist: pandas ; extra == 'results'
Requires-Dist: matplotlib ; extra == 'results'
Requires-Dist: torchviz ; extra == 'results'
Provides-Extra: sample-factory
Requires-Dist: torch !=1.13.0,<3.0,>=1.9 ; extra == 'sample-factory'
Requires-Dist: tensorboard >=1.15.0 ; extra == 'sample-factory'
Requires-Dist: tensorboardx >=2.0 ; extra == 'sample-factory'
Requires-Dist: psutil >=5.7.0 ; extra == 'sample-factory'
Requires-Dist: threadpoolctl >=2.0.0 ; extra == 'sample-factory'
Requires-Dist: colorlog ; extra == 'sample-factory'
Requires-Dist: signal-slot-mp <2.0,>=1.0.3 ; extra == 'sample-factory'
Requires-Dist: filelock ; extra == 'sample-factory'
Requires-Dist: wandb >=0.12.9 ; extra == 'sample-factory'
